[{"id":"10177255421877","name":"bg_color","varName":"","required":false,"exposed":true,"type":"shape","sizeX":300,"sizeY":600,"left":0,"top":0,"zIndex":1,"width":300,"height":600,"pointerEvents":"none","cursor":"auto","position":"absolute","animation":{"in":{"isAnimating":false,"type":"Fade-In","ease":"Power0.easeNone","speed":1,"delay":0,"frame":"all_frames"},"out":{"isAnimating":false,"type":"Fade-Out","ease":"Power0.easeNone","speed":1,"delay":0,"frame":"all_frames"},"backin":{"isAnimating":false,"type":"Fade-Back-In","ease":"Power0.easeNone","speed":1,"delay":0,"frame":"all_frames"}},"inigo":{"isRef":false,"isChosenRef":false},"removeValues":true,"boltMojoExport":false,"hasValidName":false,"direct":{"isActive":true,"selected":false,"url":""},"bolt":{"isActive":false,"selected":false,"url":""},"mojo":{"isActive":false,"selected":false,"url":""},"isExcel":false,"backgroundColor":"#ffffff","opacity":1,"borderWidth":0,"area":180000,"borderColor":"","borderRadius":0,"borderStyle":"solid","gradientAngle":90,"gradientColors":["",""]},{"id":"87172617157921","name":"bg_img","varName":"","required":false,"exposed":true,"type":"image","sizeX":300,"sizeY":600,"left":0,"top":0,"zIndex":14,"width":300,"height":600,"pointerEvents":"none","cursor":"auto","position":"absolute","animation":{"in":{"isAnimating":false,"type":"Fade-In","ease":"Power0.easeNone","speed":1,"delay":0,"frame":"all_frames"},"out":{"isAnimating":false,"type":"Fade-Out","ease":"Power0.easeNone","speed":1,"delay":0,"frame":"all_frames"},"backin":{"isAnimating":false,"type":"Fade-Back-In","ease":"Power0.easeNone","speed":1,"delay":0,"frame":"all_frames"}},"inigo":{"isRef":false,"isChosenRef":false},"removeValues":true,"boltMojoExport":false,"hasValidName":true,"direct":{"isActive":true,"selected":false,"url":""},"bolt":{"isActive":false,"selected":false,"url":""},"mojo":{"isActive":false,"selected":false,"url":""},"isExcel":false,"scale":"inside","hAlign":"left","image":"","tint":"","location":"size","backgroundSize":"contain","backgroundPosition":"center center","isExporting":true,"isScaled":false,"exportQuality":80,"exportType":"PNG24"},{"id":"60152744222432","name":"text_bg_color","varName":"","required":false,"exposed":true,"type":"shape","sizeX":300,"sizeY":600,"left":0,"top":315,"zIndex":57,"width":301,"height":285,"pointerEvents":"none","cursor":"auto","position":"absolute","animation":{"in":{"isAnimating":false,"type":"Fade-In","ease":"Power0.easeNone","speed":1,"delay":0,"frame":"all_frames"},"out":{"isAnimating":false,"type":"Fade-Out","ease":"Power0.easeNone","speed":1,"delay":0,"frame":"all_frames"},"backin":{"isAnimating":false,"type":"Fade-Back-In","ease":"Power0.easeNone","speed":1,"delay":0,"frame":"all_frames"}},"inigo":{"isRef":false,"isChosenRef":false},"removeValues":true,"boltMojoExport":false,"hasValidName":false,"direct":{"isActive":true,"selected":false,"url":""},"bolt":{"isActive":false,"selected":false,"url":""},"mojo":{"isActive":false,"selected":false,"url":""},"isExcel":false,"backgroundColor":"#f7f6f6","opacity":1,"borderWidth":0,"area":-85785,"borderColor":"","borderRadius":0,"borderStyle":"solid","gradientAngle":90,"gradientColors":["",""]},{"id":"98787929303944","name":"cta_text","varName":"","required":false,"exposed":true,"type":"text","sizeX":300,"sizeY":600,"left":32,"top":485,"zIndex":66,"width":236,"height":17,"pointerEvents":"none","cursor":"auto","position":"absolute","animation":{"in":{"isAnimating":true,"type":"Fade-In","ease":"Power0.easeNone","speed":1.3,"delay":0,"frame":"frame_2_in"},"out":{"isAnimating":false,"type":"Fade-Out","ease":"Power0.easeNone","speed":1,"delay":0,"frame":"all_frames"},"backin":{"isAnimating":false,"type":"Fade-Back-In","ease":"Power0.easeNone","speed":1,"delay":0,"frame":"all_frames"}},"inigo":{"isRef":false,"isChosenRef":false},"removeValues":true,"boltMojoExport":false,"hasValidName":true,"direct":{"isActive":true,"selected":false,"url":""},"bolt":{"isActive":false,"selected":false,"url":""},"mojo":{"isActive":false,"selected":false,"url":""},"isExcel":false,"dependency":false,"text":"JETZT SHOPPEN »","caret":{"text":"A","font":"10000","attached":true,"position":"last","color":"","spacingAmount":1,"yOffset":0.5},"legalTrigger":false,"linkedTo":{"isLinked":false,"rotator":"","images":[],"numElements":0},"hAlign":"left","color":"#000000","font":{"id":10950,"regular_id":null,"bold_id":null,"italic_id":null,"bold_italic_id":null,"name":"Roboto","style":"Regular","src":"Roboto-Regular.ttf","disabled":false,"comments":null,"created":"2014-10-27 09:15:22","updated":"2014-10-27 10:12:22","updated_by":null,"version":1},"fontSize":14,"lineHeight":1,"tracking":0,"minFontSize":4,"vAlign":"middle","marginTop":0,"marginBottom":0,"backgroundColor":"","padding":"","forceLineHeight":true,"caretEnabled":false,"maxChar":"16","charType":"Uppercase"},{"id":"68231103243306","name":"f2_headline_text","varName":"","required":false,"exposed":true,"type":"text","sizeX":300,"sizeY":600,"left":32,"top":324,"zIndex":75,"width":236,"height":154,"pointerEvents":"none","cursor":"auto","position":"absolute","animation":{"in":{"isAnimating":true,"type":"Fade-In","ease":"Power0.easeNone","speed":1.3,"delay":0,"frame":"frame_2_in"},"out":{"isAnimating":false,"type":"Fade-Out","ease":"Power0.easeNone","speed":1,"delay":0,"frame":"all_frames"},"backin":{"isAnimating":false,"type":"Fade-Back-In","ease":"Power0.easeNone","speed":1,"delay":0,"frame":"all_frames"}},"inigo":{"isRef":false,"isChosenRef":false},"removeValues":true,"boltMojoExport":false,"hasValidName":false,"direct":{"isActive":true,"selected":false,"url":""},"bolt":{"isActive":false,"selected":false,"url":""},"mojo":{"isActive":false,"selected":false,"url":""},"isExcel":false,"dependency":false,"text":"Auffallen mit Statement Sonnenbrillen","caret":{"text":"A","font":"10000","attached":true,"position":"last","color":"","spacingAmount":1,"yOffset":0.5},"legalTrigger":false,"linkedTo":{"isLinked":false,"rotator":"","images":[],"numElements":0},"hAlign":"left","color":"#000000","font":{"id":11845,"regular_id":10581,"bold_id":10579,"italic_id":10582,"bold_italic_id":10580,"name":"RobotoSlab","style":"Family","src":null,"disabled":false,"comments":null,"created":"2017-05-30 21:20:08.625912","updated":"2017-05-30 21:20:08.625912","updated_by":"eking","version":1},"fontSize":32,"lineHeight":1.16,"tracking":0,"minFontSize":4,"vAlign":"middle","marginTop":0,"marginBottom":0,"backgroundColor":"","padding":"","forceLineHeight":true,"caretEnabled":false,"maxChar":"45","charType":"Title Case"},{"id":"38620490534231","name":"f1_headline_text","varName":"","required":false,"exposed":true,"type":"text","sizeX":300,"sizeY":600,"left":32,"top":342,"zIndex":92,"width":236,"height":142,"pointerEvents":"none","cursor":"auto","position":"absolute","animation":{"in":{"isAnimating":true,"type":"Fade-In","ease":"Power0.easeNone","speed":1.3,"delay":0,"frame":"frame_1_in"},"out":{"isAnimating":true,"type":"Fade-Out","ease":"Power0.easeNone","speed":1,"delay":5,"frame":"frame_1_out"},"backin":{"isAnimating":false,"type":"Fade-Back-In","ease":"Power0.easeNone","speed":1,"delay":0,"frame":"all_frames"}},"inigo":{"isRef":false,"isChosenRef":false},"removeValues":true,"boltMojoExport":false,"hasValidName":false,"direct":{"isActive":true,"selected":false,"url":""},"bolt":{"isActive":false,"selected":false,"url":""},"mojo":{"isActive":false,"selected":false,"url":""},"isExcel":false,"dependency":false,"text":"FESTIVAL READY SHADES","caret":{"text":"A","font":"10000","attached":true,"position":"last","color":"","spacingAmount":1,"yOffset":0.5},"legalTrigger":false,"linkedTo":{"isLinked":false,"rotator":"","images":[],"numElements":0},"hAlign":"center","color":"#000000","font":{"id":11845,"regular_id":10581,"bold_id":10579,"italic_id":10582,"bold_italic_id":10580,"name":"RobotoSlab","style":"Family","src":null,"disabled":false,"comments":null,"created":"2017-05-30 21:20:08.625912","updated":"2017-05-30 21:20:08.625912","updated_by":"eking","version":1},"fontSize":36,"lineHeight":1.06,"tracking":0,"minFontSize":4,"vAlign":"middle","marginTop":0,"marginBottom":0,"backgroundColor":"","padding":"","forceLineHeight":true,"caretEnabled":false,"maxChar":"40","charType":"Uppercase"},{"id":"64953187992796","name":"badge_img","varName":"","required":false,"exposed":true,"type":"image","sizeX":300,"sizeY":600,"left":32,"top":507,"zIndex":103,"width":236,"height":0,"pointerEvents":"none","cursor":"auto","position":"absolute","animation":{"in":{"isAnimating":false,"type":"Fade-In","ease":"Power0.easeNone","speed":1,"delay":0,"frame":"all_frames"},"out":{"isAnimating":false,"type":"Fade-Out","ease":"Power0.easeNone","speed":1,"delay":0,"frame":"all_frames"},"backin":{"isAnimating":false,"type":"Fade-Back-In","ease":"Power0.easeNone","speed":1,"delay":0,"frame":"all_frames"}},"inigo":{"isRef":false,"isChosenRef":false},"removeValues":true,"boltMojoExport":false,"hasValidName":true,"direct":{"isActive":true,"selected":false,"url":""},"bolt":{"isActive":false,"selected":false,"url":""},"mojo":{"isActive":false,"selected":false,"url":""},"isExcel":false,"scale":"inside","hAlign":"left","image":"","tint":"","location":"size","backgroundSize":"contain","backgroundPosition":"center center","isExporting":true,"isScaled":false,"exportQuality":80,"exportType":"PNG24"},{"id":"56712378934026","name":"cat3_img","varName":"","required":true,"exposed":true,"type":"image","sizeX":300,"sizeY":600,"left":62,"top":212,"zIndex":128,"width":176,"height":86,"pointerEvents":"none","cursor":"auto","position":"absolute","animation":{"in":{"isAnimating":true,"type":"Fade-In","ease":"Power0.easeNone","speed":1.3,"delay":0,"frame":"frame_2_in"},"out":{"isAnimating":false,"type":"Fade-Out","ease":"Power0.easeNone","speed":1,"delay":0,"frame":"all_frames"},"backin":{"isAnimating":false,"type":"Fade-Back-In","ease":"Power0.easeNone","speed":1,"delay":0,"frame":"all_frames"}},"inigo":{"isRef":false,"isChosenRef":false},"removeValues":true,"boltMojoExport":false,"hasValidName":false,"direct":{"isActive":true,"selected":false,"url":""},"bolt":{"isActive":false,"selected":false,"url":""},"mojo":{"isActive":false,"selected":false,"url":""},"isExcel":false,"scale":"inside","hAlign":"left","image":"","tint":"","location":"crop","backgroundSize":"contain","backgroundPosition":"center center","isExporting":true,"isScaled":true,"exportQuality":80,"exportType":"PNG24"},{"id":"77887589205056","name":"cat2_img","varName":"","required":true,"exposed":true,"type":"image","sizeX":300,"sizeY":600,"left":62,"top":116,"zIndex":165,"width":176,"height":86,"pointerEvents":"none","cursor":"auto","position":"absolute","animation":{"in":{"isAnimating":true,"type":"Fade-In","ease":"Power0.easeNone","speed":1.3,"delay":0,"frame":"frame_2_in"},"out":{"isAnimating":false,"type":"Fade-Out","ease":"Power0.easeNone","speed":1,"delay":0,"frame":"all_frames"},"backin":{"isAnimating":false,"type":"Fade-Back-In","ease":"Power0.easeNone","speed":1,"delay":0,"frame":"all_frames"}},"inigo":{"isRef":false,"isChosenRef":false},"removeValues":true,"boltMojoExport":false,"hasValidName":false,"direct":{"isActive":true,"selected":false,"url":""},"bolt":{"isActive":false,"selected":false,"url":""},"mojo":{"isActive":false,"selected":false,"url":""},"isExcel":false,"scale":"inside","hAlign":"left","image":"","tint":"","location":"crop","backgroundSize":"contain","backgroundPosition":"center center","isExporting":true,"isScaled":true,"exportQuality":80,"exportType":"PNG24"},{"id":"60461586667225","name":"cat1_img","varName":"","required":true,"exposed":true,"type":"image","sizeX":300,"sizeY":600,"left":62,"top":21,"zIndex":202,"width":176,"height":86,"pointerEvents":"none","cursor":"auto","position":"absolute","animation":{"in":{"isAnimating":true,"type":"Fade-In","ease":"Power0.easeNone","speed":1.3,"delay":0,"frame":"frame_2_in"},"out":{"isAnimating":false,"type":"Fade-Out","ease":"Power0.easeNone","speed":1,"delay":0,"frame":"all_frames"},"backin":{"isAnimating":false,"type":"Fade-Back-In","ease":"Power0.easeNone","speed":1,"delay":0,"frame":"all_frames"}},"inigo":{"isRef":false,"isChosenRef":false},"removeValues":true,"boltMojoExport":false,"hasValidName":false,"direct":{"isActive":true,"selected":false,"url":""},"bolt":{"isActive":false,"selected":false,"url":""},"mojo":{"isActive":false,"selected":false,"url":""},"isExcel":false,"scale":"inside","hAlign":"left","image":"","tint":"","location":"crop","backgroundSize":"contain","backgroundPosition":"center center","isExporting":true,"isScaled":true,"exportQuality":80,"exportType":"PNG24"},{"id":"74591566668823","name":"lifestyle_img","varName":"","required":false,"exposed":true,"type":"image","sizeX":300,"sizeY":600,"left":0,"top":0,"zIndex":239,"width":300,"height":315,"pointerEvents":"none","cursor":"auto","position":"absolute","animation":{"in":{"isAnimating":true,"type":"Fade-In","ease":"Power0.easeNone","speed":1.3,"delay":0,"frame":"frame_1_in"},"out":{"isAnimating":true,"type":"Fade-Out","ease":"Power0.easeNone","speed":1,"delay":5,"frame":"frame_1_out"},"backin":{"isAnimating":false,"type":"Fade-Back-In","ease":"Power0.easeNone","speed":1,"delay":0,"frame":"all_frames"}},"inigo":{"isRef":false,"isChosenRef":false},"removeValues":true,"boltMojoExport":false,"hasValidName":true,"direct":{"isActive":true,"selected":false,"url":""},"bolt":{"isActive":false,"selected":false,"url":""},"mojo":{"isActive":false,"selected":false,"url":""},"isExcel":false,"scale":"inside","hAlign":"left","image":"","tint":"","location":"crop","backgroundSize":"contain","backgroundPosition":"center center","isExporting":true,"isScaled":true,"exportQuality":80,"exportType":"PNG24"},{"id":"42564085870981","name":"logo_img","varName":"","required":true,"exposed":true,"type":"image","sizeX":300,"sizeY":600,"left":86,"top":527,"zIndex":482,"width":128,"height":37,"pointerEvents":"none","cursor":"auto","position":"absolute","animation":{"in":{"isAnimating":false,"type":"Fade-In","ease":"Power0.easeNone","speed":1,"delay":0,"frame":"all_frames"},"out":{"isAnimating":false,"type":"Fade-Out","ease":"Power0.easeNone","speed":1,"delay":0,"frame":"all_frames"},"backin":{"isAnimating":false,"type":"Fade-Back-In","ease":"Power0.easeNone","speed":1,"delay":0,"frame":"all_frames"}},"inigo":{"isRef":false,"isChosenRef":false},"removeValues":true,"boltMojoExport":false,"hasValidName":true,"direct":{"isActive":true,"selected":false,"url":""},"bolt":{"isActive":false,"selected":false,"url":""},"mojo":{"isActive":false,"selected":false,"url":""},"isExcel":false,"scale":"inside","hAlign":"left","image":"","tint":"","location":"size","backgroundSize":"contain","backgroundPosition":"center center","isExporting":true,"isScaled":false,"exportQuality":80,"exportType":"PNG24"},{"id":"34506013197824","name":"style_img","varName":"","required":false,"exposed":true,"type":"image","sizeX":300,"sizeY":600,"left":0,"top":0,"zIndex":1016,"width":300,"height":600,"pointerEvents":"none","cursor":"auto","position":"absolute","animation":{"in":{"isAnimating":false,"type":"Fade-In","ease":"Power0.easeNone","speed":1,"delay":0,"frame":"all_frames"},"out":{"isAnimating":false,"type":"Fade-Out","ease":"Power0.easeNone","speed":1,"delay":0,"frame":"all_frames"},"backin":{"isAnimating":false,"type":"Fade-Back-In","ease":"Power0.easeNone","speed":1,"delay":0,"frame":"all_frames"}},"inigo":{"isRef":false,"isChosenRef":false},"removeValues":true,"boltMojoExport":false,"hasValidName":true,"direct":{"isActive":true,"selected":false,"url":""},"bolt":{"isActive":false,"selected":false,"url":""},"mojo":{"isActive":false,"selected":false,"url":""},"isExcel":false,"scale":"inside","hAlign":"left","image":"","tint":"","location":"size","backgroundSize":"contain","backgroundPosition":"center center","isExporting":true,"isScaled":false,"exportQuality":80,"exportType":"PNG24"},{"id":"62892515351996","name":"fg_img","varName":"","required":false,"exposed":true,"type":"image","sizeX":300,"sizeY":600,"left":0,"top":0,"zIndex":1029,"width":300,"height":600,"pointerEvents":"none","cursor":"auto","position":"absolute","animation":{"in":{"isAnimating":false,"type":"Fade-In","ease":"Power0.easeNone","speed":1,"delay":0,"frame":"all_frames"},"out":{"isAnimating":false,"type":"Fade-Out","ease":"Power0.easeNone","speed":1,"delay":0,"frame":"all_frames"},"backin":{"isAnimating":false,"type":"Fade-Back-In","ease":"Power0.easeNone","speed":1,"delay":0,"frame":"all_frames"}},"inigo":{"isRef":false,"isChosenRef":false},"removeValues":true,"boltMojoExport":false,"hasValidName":true,"direct":{"isActive":true,"selected":false,"url":""},"bolt":{"isActive":false,"selected":false,"url":""},"mojo":{"isActive":false,"selected":false,"url":""},"isExcel":false,"scale":"inside","hAlign":"left","image":"","tint":"","location":"size","backgroundSize":"contain","backgroundPosition":"center center","isExporting":true,"isScaled":false,"exportQuality":80,"exportType":"PNG24"}]